src/alu/alu.v
// instruction: 32-bit instruction
// regA/B: 32-bit data in registerA(addr=00000), registerB(addr=00001)
// result: 32-bit result of Alu execution
// flags: 3-bit alu flag
// flags[2] : zero flag
// flags[1] : negative flag
// flags[0] : overflow flag 
module alu(instruction, regA, regB, result, flags);
    input [31:0] instruction, regA, regB; // the address of regA is 00000, the address of regB is 00001
    output [31:0] result;
    output [2:0] flags; // the first bit is zero flag, the second bit is negative flag, the third bit is overflow flag.

	/*** Constants ***/

	localparam  // R type
		OP_R = 6'b000000,
		FUNC_SLL = 6'b000000,
		FUNC_SRL = 6'b000010,
		FUNC_SRA = 6'b000011,
		FUNC_SLLV = 6'b000100,
		FUNC_SRLV = 6'b000110,
		FUNC_SRAV = 6'b000111,
		FUNC_JR = 6'b001000,
		FUNC_ADD = 6'b100000,
		FUNC_ADDU = 6'b100001,
		FUNC_SUB = 6'b100010,
		FUNC_SUBU = 6'b100011,
		FUNC_AND = 6'b100100,
		FUNC_OR = 6'b100101,
		FUNC_XOR = 6'b100110,
		FUNC_NOR = 6'b100111,
		FUNC_SLT = 6'b101010,
		FUNC_SLTU = 6'b101011;
    
    localparam  // I type
		OP_BEQ      = 6'b000100,
		OP_BNE 		= 6'b000101,
		OP_ADDI 	= 6'b001000,
		OP_ADDIU 	= 6'b001001,
		OP_ANDI 	= 6'b001100,
		OP_ORI 		= 6'b001101,
		OP_XORI 	= 6'b001110,
		OP_LW 		= 6'b100011,
		OP_SW 		= 6'b101011,
		OP_SLTI 	= 6'b001010,
		OP_SLTIU 	= 6'b001011;

    localparam
		ALU_ADD    	= 0,
		ALU_ADDU	= 1,
		ALU_SUB    	= 2,
		ALU_SUBU 	= 3,
		ALU_AND    	= 4,
		ALU_NOR		= 5,
		ALU_OR		= 6,
		ALU_XOR		= 7,
		ALU_SLL		= 8,
		ALU_SLLV	= 9,
		ALU_SRL		= 10,
		ALU_SRLV	= 11,
		ALU_SRA		= 12,
		ALU_SRAV	= 13,
		ALU_SLT		= 14,
		ALU_SLTU    = 15,
		ALU_ZERO 	= 16;

	/*** Signals ***/

	wire [5:0] opcode;
    wire [4:0] rs, rt, rd, sa;
    wire [5:0] func;
    wire [15:0] imm;
	wire [31:0] valA, valB;
	wire [31:0] sign_extended_imm, unsign_extended_imm;
	wire [31:0] unsign_extended_sa;
	wire signed [31:0] aluA, aluB;

	// Control signals
	wire [1:0] ALUOp;
	wire ALUSrcA, ALUSrcB;
	wire [4:0] ALUControl;

	/*** Logic Implementation ***/

	assign opcode = instruction[31:26];
    assign rs     = instruction[25:21];
    assign rt     = instruction[20:16];
    assign rd     = instruction[15:11];
    assign sa     = instruction[10: 6];
    assign func   = instruction[ 5: 0];
    assign imm    = instruction[15: 0];

	// 0: rs    1: sa
    assign ALUSrcA = 
    	opcode == OP_R & (func == FUNC_SLL | func == FUNC_SRA | func == FUNC_SRL);
    
    // 0: rt   1: imm
    assign ALUSrcB = 
    	~(opcode == OP_R & func != FUNC_JR | opcode == OP_BNE | opcode == OP_BEQ);

	// 00: addition for loads and stores
    // 01: subtraction for branch
    // 10: determined by the operation encoded in the funct field
    // 11: other I type instructions
    assign ALUOp = 
		opcode == OP_LW | opcode == OP_SW ? 2'b00 :
		opcode == OP_BEQ | opcode == OP_BNE ? 2'b01 :
		opcode == OP_R ? 2'b10 :
		2'b11;

	assign valA = 
		rs == 5'b00000 ? regA :
		regB;
	assign valB = 
		rt == 5'b00000 ? regA :
		regB;

	assign sign_extended_imm = imm[15] ? {{16{imm[15]}},imm} : {16'b0,imm};
	assign unsign_extended_imm = {16'b0,imm};
    assign unsign_extended_sa  = {27'b0,sa};

	assign aluA = ALUSrcA ? unsign_extended_sa : valA;
	assign aluB = 
		ALUSrcB ? (opcode == OP_ADDI | opcode == OP_SLTI | opcode == OP_LW | opcode == OP_SW ? sign_extended_imm : unsign_extended_imm) :
		valB;

	assign ALUControl = 
        (ALUOp == 2'b10 & func == FUNC_ADD) | ALUOp == 2'b00 | (ALUOp == 2'b11 & opcode == OP_ADDI) ? ALU_ADD :
        (ALUOp == 2'b10 & func == FUNC_ADDU) | (ALUOp == 2'b11 & opcode == OP_ADDIU) ? ALU_ADDU :
        (ALUOp == 2'b10 & func == FUNC_SUB) | ALUOp == 2'b01 ? ALU_SUB :
        ALUOp == 2'b10 & func == FUNC_SUBU ? ALU_SUBU :
        (ALUOp == 2'b10 & func == FUNC_AND) | (ALUOp == 2'b11 & opcode == OP_ANDI) ? ALU_AND :
        ALUOp == 2'b10 & func == FUNC_NOR ? ALU_NOR :
        (ALUOp == 2'b10 & func == FUNC_OR) | (ALUOp == 2'b11 & opcode == OP_ORI) ? ALU_OR :
        (ALUOp == 2'b10 & func == FUNC_XOR) | (ALUOp == 2'b11 & opcode == OP_XORI) ? ALU_XOR :
        ALUOp == 2'b10 & func == FUNC_SLL ? ALU_SLL :
        ALUOp == 2'b10 & func == FUNC_SLLV ? ALU_SLLV :
        ALUOp == 2'b10 & func == FUNC_SRL ? ALU_SRL :
        ALUOp == 2'b10 & func == FUNC_SRLV ? ALU_SRLV :
        ALUOp == 2'b10 & func == FUNC_SRA ? ALU_SRA :
        ALUOp == 2'b10 & func == FUNC_SRAV ? ALU_SRAV :
        (ALUOp == 2'b10 & func == FUNC_SLT) | (ALUOp == 2'b11 & opcode == OP_SLTI) ? ALU_SLT :
		(ALUOp == 2'b10 & func == FUNC_SLTU) | (ALUOp == 2'b11 & opcode == OP_SLTIU) ? ALU_SLTU :
        ALU_ZERO;

	assign result = 
		ALUControl == ALU_ADD | ALUControl == ALU_ADDU ? aluA + aluB :
		ALUControl == ALU_SUB | ALUControl == ALU_SUBU | ALUControl == ALU_SLT | ALUControl == ALU_SLTU ? aluA - aluB :
		ALUControl == ALU_AND ? aluA & aluB :
		ALUControl == ALU_NOR ? ~(aluA | aluB) :
		ALUControl == ALU_OR ? aluA | aluB :
		ALUControl == ALU_XOR ? aluA ^ aluB :
		ALUControl == ALU_SLL ? aluB << aluA :
		ALUControl == ALU_SLLV ? aluB << aluA[4:0] : // 3
		ALUControl == ALU_SRL ? aluB >> aluA :
		ALUControl == ALU_SRLV ? aluB >> (aluA % (1 << 5)) : // 3
		ALUControl == ALU_SRA ? $signed(aluB) >>> aluA :
		ALUControl == ALU_SRAV ? $signed(aluB) >>> (aluA % (1 << 5)) : // 3
		0;

	assign set_flags = 
        func == FUNC_ADD | func == OP_ADDI | func == FUNC_SUB | func == OP_BEQ | 
        func == OP_BNE | func == FUNC_SLT | func == FUNC_SLTU;	

	// ZF
	assign flags[2] = 
	 	opcode == OP_BNE | opcode == OP_BEQ ? result == 0 :
		0;
	// SF
	assign flags[1] = 
		opcode == OP_R & (func == FUNC_SLT | func ==FUNC_SLTU) | opcode == OP_SLTI | opcode == OP_SLTIU ? result[31] :
		0;
	// OF
	assign flags[0] = 
		opcode == OP_R & func == FUNC_ADD | opcode == OP_ADDI ? aluA[31] == aluB[31] & aluA[31] != result[31] :
		opcode == OP_R & func == FUNC_SUB ? aluA[31] != aluB[31] & aluA[31] != result[31] :
		0;
    
endmodule

src/alu/test_alu.v
`include "alu.v"
`timescale 1ns/1ps

module test();
    reg  [31:0] instruction;
    reg  [31:0] regA;
    reg  [31:0] regB;
    reg  [31:0] exp_result;
    reg  [2:0] exp_flags;
    reg  [7:0] testID;
    wire [31:0] result;
    wire [2:0] flags;

    initial begin
        $dumpfile("test.vcd");
        $dumpvars;
    end

    initial begin
        $display("\ninitialize...");
        $monitor("INPUT: instruction = 32'b%b\nregA = 32'h%h, regB = 32'h%h\nOUTPUT: result = 32'h%h, flags = 3'b%b\nEXPECTED: result = 32'h%h, flags = 3'b%b", 
                 instruction, regA, regB, result, flags, exp_result, exp_flags);
        instruction = 32'b0;
        regA = 32'b0; 
        regB = 32'b0;
        exp_result = 32'b0;
        exp_flags = 3'b0;
        testID = 0;
        #500

        $display("\n##############################\nTests for R Type\n##############################"); 
        $display("\nTEST %d: add test (overflow): 127 + 1 = -128", testID);
        instruction = 32'h00200020;   // testing for add overflow
        regA = 32'h7FFFFFFF;
        regB = 32'h00000001;
        exp_result = 32'h80000000;
        exp_flags = 3'b001;
        testID += 1;
        #100
        $display("\nTEST %d: add test: 1 + 2 = 3", testID);
        instruction = 32'h00010020;   // testing for add normal
        regA = 32'h00000001;
        regB = 32'h00000002;
        exp_result = 32'h00000003;
        exp_flags = 3'b000;
        testID += 1;
        #100
        $display("\nTEST %d: sub test (overflow): 127 - -1 = -128", testID);
        instruction = 32'h00010022;   // testing for sub overflow
        regA = 32'h7FFFFFFF;
        regB = 32'hFFFFFFFF;
        exp_result = 32'h80000000;
        exp_flags = 3'b001;
        testID += 1;
        #100
        $display("\nTEST %d: sub test: 4 - 3 = 1", testID);
        instruction = 32'h00010022;   // testing for sub normal
        regA = 32'h00000004;
        regB = 32'h00000003;
        exp_result = 32'h00000001;
        exp_flags = 3'b000;
        testID += 1;
        #100
        $display("\nTEST %d: addu test: 127 + 1 = 128", testID);
        instruction = 32'h00200021;   // testing for addu 
        regA = 32'h7FFFFFFF;
        regB = 32'h00000001;
        exp_result = 32'h80000000;
        exp_flags = 3'b000;
        testID += 1;
        #100 
        $display("\nTEST %d: subu test: 127 - -1= 128", testID);
        instruction = 32'h00010023;   // testing for subu
        regA = 32'h7FFFFFFF;
        regB = 32'hFFFFFFFF;
        exp_result = 32'h80000000;
        exp_flags = 3'b000;
        testID += 1;
        #100
        $display("\nTEST %d: and test: 0xFFFF FFFF & 0x0000 0001 = 1", testID);
        instruction = 32'h00010024;   // testing for and
        regA = 32'hFFFFFFFF;
        regB = 32'h00000001;
        exp_result = 32'h00000001;
        exp_flags = 3'b000;
        testID += 1;
        #100
        $display("\nTEST %d: or test: 0x0000 0000 | 0x0000 0001 = 0x0000 0001", testID);
        instruction = 32'h00200025;   // testing for or
        regA = 32'h00000000;
        regB = 32'h00000001;
        exp_result = 32'h00000001;
        exp_flags = 3'b000;
        testID += 1;
        #100
        $display("\nTEST %d: xor test: 0xFFFF FFFF ^ 0x0000 000F = 0xFFFF FFF0", testID);
        instruction = 32'h00200026;  // testing for xor
        regA = 32'hFFFFFFFF;
        regB = 32'h0000000F;
        exp_result = 32'hFFFFFFF0;
        exp_flags = 3'b000;
        testID += 1;
        #100
        $display("\nTEST %d: nor test: ~(0x0000 0000 | 0xFFFF FFFF) = 0x0000 0000", testID);
        instruction = 32'h00200027;  //testing for nor
        regA = 32'h00000000;
        regB = 32'hFFFFFFFF;
        exp_result = 32'h00000000;
        exp_flags = 3'b000;  
        testID += 1;     
        #100
        $display("\nTEST %d: slt test (set): 0 < 1", testID);
        instruction = 32'h0001002A;  // testing for slt
        regA = 32'h00000000;
        regB = 32'h00000001;
        exp_result = 32'hFFFFFFFF;
        exp_flags = 3'b010;
        testID += 1;
        #100
        $display("\nTEST %d: slt test (not set): 1 > 0", testID);
        instruction = 32'h0001002A;
        regA = 32'h00000001;
        regB = 32'h00000000;
        exp_result = 32'h00000001;
        exp_flags = 3'b000;
        testID += 1;
        #100
        $display("\nTEST %d: sltu test (set): 0x0000 0000 < 0xFFFF FFFF", testID);
        instruction = 32'h0001002B;  // testing for sltu
        regA = 32'h00000000;
        regB = 32'hFFFFFFFF;
        exp_result = 32'h00000001;
        exp_flags = 3'b000;
        testID += 1;
        #100
        $display("\nTEST %d: sltu test (not set): 0xFFFF FFFF > 0xFFFF FFFE", testID);
        instruction = 32'h0001002B;  // testing for sltu
        regA = 32'hFFFFFFFF;
        regB = 32'hFFFFFFFE;
        exp_result = 32'h00000001;
        exp_flags = 3'b000;
        testID += 1;
        #100
        $display("\nTEST %d: sll test: 0x0000 0001 << 10 = 0x0000 0400", testID);
        instruction = 32'h00010280;  // testing for sll
        regA = 32'h00000000;
        regB = 32'h00000001;
        exp_result = 32'h00000400;
        exp_flags = 3'b000;
        testID += 1;
        #100
        $display("\nTEST %d: srl test: 0xF0000 0000 >> 10 = 0x003C 0000", testID);
        instruction = 32'h00010282;  //testing for srl
        regA = 32'h00000000;
        regB = 32'hF0000000;
        exp_result = 32'h003C0000;
        exp_flags = 3'b000;
        testID += 1;
        #100
        $display("\nTEST %d: sllv test: 0x0000 0001 << 16 = 0x0001 0000", testID);
        instruction = 32'h00010004; //testing for sllv
        regA = 32'h00000010;
        regB = 32'h00000001;
        exp_result = 32'h00010000;
        exp_flags = 3'b000;
        testID += 1;
        #100
        $display("\nTEST %d: srlv test: 0xF000 0000 >> 4 = 0x0F00 0000", testID);
        instruction = 32'h00010006; // testing for srlv
        regA = 32'h00000004;
        regB = 32'hF0000000;
        exp_result = 32'h0F000000;
        exp_flags = 3'b000;
        testID += 1;
        #100
        $display("\nTEST %d: srav test: 0xF000 0000 >> 4 = 0xFF00 0000", testID);
        instruction = 32'h00010007; // testing for srav
        regA = 32'h00000004;
        regB = 32'hF0000000;
        exp_result = 32'hFF000000;
        exp_flags = 3'b000;
        testID += 1;
        #100
        $display("\nTEST %d: sra test: 0xF000 0000 >> 2 = 0xCF00 0000", testID);
        instruction = 32'h00010083; // testing for sra
        regA = 32'h00000004;
        regB = 32'hF0000000;
        exp_result = 32'hFC000000;
        exp_flags = 3'b000;
        testID += 1;
        #100

        $display("\n##############################\nTest for I Type\n##############################");
        $display("\nTEST %d: addi test: 0 + 1 = 1", testID);
        instruction = 32'h20200001;  // testing for addi
        regA = 32'h00000001;
        regB = 32'h00000000;
        exp_result = 32'h00000001;
        exp_flags = 3'b000;
        testID += 1;
        #100
        $display("\nTEST %d: addi test (overflow): 127 + 1 = -128", testID);
        instruction = 32'h20010001;  // testing for addi
        regA = 32'h7FFFFFFF;
        regB = 32'h00000000;
        exp_result = 32'h80000000;
        exp_flags = 3'b001;
        testID += 1;
        #100
        $display("\nTEST %d: andi test: 0xFFFF FFFF & 0x0000 0001 = 0x0000 0001", testID);
        instruction = 32'h30010001;  // testing for andi
        regA = 32'hFFFFFFFF;
        regB = 32'h00000000;
        exp_result = 32'h00000001;
        exp_flags = 3'b000;
        testID += 1;
        #100
        $display("\nTEST %d: addiu test: 0 + 129 = 129", testID);
        instruction = 32'h24208001;  //testing for addiu
        regA = 32'h00000001;
        regB = 32'h00000000;
        exp_result = 32'h00008001;
        exp_flags = 3'b000;
        testID += 1;
        #100
        $display("\nTEST %d: ori test: 0x0000 0010 | 0x0000 0001 = 0x0000 0011", testID);
        instruction = 32'h34010001; //testing for ori
        regA = 32'h00000010;
        regB = 32'h00000000;
        exp_result = 32'h00000011;
        exp_flags = 3'b000;
        testID += 1;
        #100
        $display("\nTEST %d: xori test: 0x0000 0001 ^ 0x0000 0003 = 0x0000 0002", testID);
        instruction = 32'h38010003; //testing for xori
        regA = 32'h00000001;
        regB = 32'h00000000;
        exp_result = 32'h00000002;
        exp_flags = 3'b000;
        testID += 1;
        #100
        $display("\nTEST %d: slti test (set): 0 < 1", testID);
        instruction = 32'h28010001; //testing for slti
        regA = 32'h00000000;
        regB = 32'h00000000;
        exp_result = 32'hFFFFFFFF;
        exp_flags = 3'b010;
        testID += 1;
        #100
        $display("\nTEST %d: slti test (not set): 1 > 0", testID);
        instruction = 32'h28010000; //testing for slti
        regA = 32'h00000001;
        regB = 32'h00000000;
        exp_result = 32'h00000001;
        exp_flags = 3'b000;
        testID += 1;
        #100
        $display("\nTEST %d: beq test (branch occurs): 1 == 1", testID);
        instruction = 32'h10010001; //testing for beq
        regA = 32'h00000001;
        regB = 32'h00000001;
        exp_result = 32'h00000000;
        exp_flags = 3'b100;
        testID += 1;
        #100
        $display("\nTEST %d: beq test (branch not occurs): 0 != 1", testID);
        instruction = 32'h10010001; //testing for beq
        regA = 32'h00000000;
        regB = 32'h00000001;
        exp_result = 32'hFFFFFFFF;
        exp_flags = 3'b000;
        testID += 1;
        #100
        $display("\nTEST %d: bne test (branch occurs) 1 != 0", testID);
        instruction = 32'h14010001; //testing for bne
        regA = 32'h00000001;
        regB = 32'h00000000;
        exp_result = 32'h00000001;
        exp_flags = 3'b000;
        testID += 1;
        #100
        $display("\nTEST %d: bne test (branch not occurs): 1 == 1", testID);
        instruction = 32'h14010001; //testing for bne
        regA = 32'h00000001;
        regB = 32'h00000001;
        exp_result = 32'h00000000;
        exp_flags = 3'b100;
        testID += 1;
        #100
        $display("\nTEST %d: sltiu test (set): 1 < 16", testID);
        instruction = 32'h2C010010; //testing for sltiu
        regA = 32'h00000001;
        regB = 32'h00000000;
        exp_result = 32'hFFFFFFF1;
        exp_flags = 3'b010;
        testID += 1;
        #100
        $display("\nTEST %d: sltiu test (not set): 16 == 16", testID);
        instruction = 32'h2C010010; //testing for sltiu
        regA = 32'h00000010;
        regB = 32'h00000000;
        exp_result = 32'h00000000;
        exp_flags = 3'b000;
        testID += 1;
        #100
        $display("\nTEST %d: lw test: 0x0000 F00F + 0x0000 0010 = 0xFFFF F01F", testID);
        instruction = 32'h8C01F00F; //testing for lw
        regA = 32'h00000010;
        regB = 32'h00000000;
        exp_result = 32'hFFFFF01F;
        exp_flags = 3'b000;
        testID += 1;
        #100
        $display("\nTEST %d: sw test: 0x0000 700F + 0x0000 0100 = 0x0000 710F", testID);
        instruction = 32'hAC01700F; //testing for sw
        regA = 32'h00000100;
        regB = 32'h00000000;
        exp_result = 32'h0000710F;
        exp_flags = 3'b000;
        testID += 1;
        #100
        $stop;
    end

    alu alu_test(
        .instruction( instruction ),
        .regA( regA ),
        .regB( regB ),
        .result( result ),
        .flags(flags)
    );

endmodule

src/alu/test.vcd
$date
	Sat Apr 29 10:19:36 2023
$end
$version
	Icarus Verilog
$end
$timescale
	1ps
$end
$scope module test $end
$var wire 32 ! result [31:0] $end
$var wire 3 " flags [2:0] $end
$var reg 3 # exp_flags [2:0] $end
$var reg 32 $ exp_result [31:0] $end
$var reg 32 % instruction [31:0] $end
$var reg 32 & regA [31:0] $end
$var reg 32 ' regB [31:0] $end
$var reg 8 ( testID [7:0] $end
$scope module alu_test $end
$var wire 1 ) ALUSrcA $end
$var wire 1 * ALUSrcB $end
$var wire 32 + instruction [31:0] $end
$var wire 32 , regA [31:0] $end
$var wire 32 - regB [31:0] $end
$var wire 1 . set_flags $end
$var wire 32 / valB [31:0] $end
$var wire 32 0 valA [31:0] $end
$var wire 32 1 unsign_extended_sa [31:0] $end
$var wire 32 2 unsign_extended_imm [31:0] $end
$var wire 32 3 sign_extended_imm [31:0] $end
$var wire 5 4 sa [4:0] $end
$var wire 5 5 rt [4:0] $end
$var wire 5 6 rs [4:0] $end
$var wire 32 7 result [31:0] $end
$var wire 5 8 rd [4:0] $end
$var wire 6 9 opcode [5:0] $end
$var wire 16 : imm [15:0] $end
$var wire 6 ; func [5:0] $end
$var wire 3 < flags [2:0] $end
$var wire 32 = aluB [31:0] $end
$var wire 32 > aluA [31:0] $end
$var wire 2 ? ALUOp [1:0] $end
$var wire 5 @ ALUControl [4:0] $end
$upscope $end
$upscope $end
$enddefinitions $end
#0
$dumpvars
b1000 @
b10 ?
b0 >
b0 =
b0 <
b0 ;
b0 :
b0 9
b0 8
b0 7
b0 6
b0 5
b0 4
b0 3
b0 2
b0 1
b0 0
b0 /
0.
b0 -
b0 ,
b0 +
0*
1)
b0 (
b0 '
b0 &
b0 %
b0 $
b0 #
b0 "
b0 !
$end
#500000
b1 "
b1 <
b10000000000000000000000000000000 !
b10000000000000000000000000000000 7
1.
b0 @
b1 >
0)
b1111111111111111111111111111111 =
b100000 3
b1 0
b1111111111111111111111111111111 /
b1 6
b100000 ;
b100000 2
b100000 :
b1 (
b1 #
b10000000000000000000000000000000 $
b1 '
b1 -
b1111111111111111111111111111111 &
b1111111111111111111111111111111 ,
b1000000000000000100000 %
b1000000000000000100000 +
#600000
b0 "
b0 <
b11 !
b11 7
b10 =
b10 /
b0 6
b1 5
b10 (
b0 #
b11 $
b10 '
b10 -
b1 &
b1 ,
b10000000000100000 %
b10000000000100000 +
#700000
b1 "
b1 <
b10 @
b10000000000000000000000000000000 !
b10000000000000000000000000000000 7
b11111111111111111111111111111111 =
b1111111111111111111111111111111 >
b100010 3
b11111111111111111111111111111111 /
b1111111111111111111111111111111 0
b100010 ;
b100010 2
b100010 :
b11 (
b1 #
b10000000000000000000000000000000 $
b11111111111111111111111111111111 '
b11111111111111111111111111111111 -
b1111111111111111111111111111111 &
b1111111111111111111111111111111 ,
b10000000000100010 %
b10000000000100010 +
#800000
b0 "
b0 <
b1 !
b1 7
b11 =
b100 >
b11 /
b100 0
b100 (
b0 #
b1 $
b11 '
b11 -
b100 &
b100 ,
#900000
b1 @
0.
b10000000000000000000000000000000 !
b10000000000000000000000000000000 7
b1111111111111111111111111111111 =
b1 >
b100001 3
b1111111111111111111111111111111 /
b1 0
b1 6
b0 5
b100001 ;
b100001 2
b100001 :
b101 (
b10000000000000000000000000000000 $
b1 '
b1 -
b1111111111111111111111111111111 &
b1111111111111111111111111111111 ,
b1000000000000000100001 %
b1000000000000000100001 +
#1000000
b11 @
b10000000000000000000000000000000 !
b10000000000000000000000000000000 7
b11111111111111111111111111111111 =
b1111111111111111111111111111111 >
b11111111111111111111111111111111 /
b100011 3
b1111111111111111111111111111111 0
b0 6
b1 5
b100011 ;
b100011 2
b100011 :
b110 (
b11111111111111111111111111111111 '
b11111111111111111111111111111111 -
b10000000000100011 %
b10000000000100011 +
#1100000
b100 @
b1 !
b1 7
b1 =
b11111111111111111111111111111111 >
b100100 3
b1 /
b11111111111111111111111111111111 0
b100100 ;
b100100 2
b100100 :
b111 (
b1 $
b1 '
b1 -
b11111111111111111111111111111111 &
b11111111111111111111111111111111 ,
b10000000000100100 %
b10000000000100100 +
#1200000
b110 @
b1 !
b1 7
b0 =
b1 >
b0 /
b100101 3
b1 0
b1 6
b0 5
b100101 ;
b100101 2
b100101 :
b1000 (
b0 &
b0 ,
b1000000000000000100101 %
b1000000000000000100101 +
#1300000
b111 @
b11111111111111111111111111110000 !
b11111111111111111111111111110000 7
b1111 >
b11111111111111111111111111111111 =
b100110 3
b1111 0
b11111111111111111111111111111111 /
b100110 ;
b100110 2
b100110 :
b1001 (
b11111111111111111111111111110000 $
b1111 '
b1111 -
b11111111111111111111111111111111 &
b11111111111111111111111111111111 ,
b1000000000000000100110 %
b1000000000000000100110 +
#1400000
b0 !
b0 7
b101 @
b11111111111111111111111111111111 >
b0 =
b100111 3
b11111111111111111111111111111111 0
b0 /
b100111 ;
b100111 2
b100111 :
b1010 (
b0 $
b11111111111111111111111111111111 '
b11111111111111111111111111111111 -
b0 &
b0 ,
b1000000000000000100111 %
b1000000000000000100111 +
#1500000
b10 "
b10 <
b1110 @
b11111111111111111111111111111111 !
b11111111111111111111111111111111 7
b1 =
1.
b0 >
b1 /
b101010 3
b0 0
b0 6
b1 5
b101010 ;
b101010 2
b101010 :
b1011 (
b10 #
b11111111111111111111111111111111 $
b1 '
b1 -
b10000000000101010 %
b10000000000101010 +
#1600000
b0 "
b0 <
b1 !
b1 7
b0 =
b1 >
b0 /
b1 0
b1100 (
b0 #
b1 $
b0 '
b0 -
b1 &
b1 ,
#1700000
b1111 @
b11111111111111111111111111111111 =
b0 >
b101011 3
b11111111111111111111111111111111 /
b0 0
b101011 ;
b101011 2
b101011 :
b1101 (
b11111111111111111111111111111111 '
b11111111111111111111111111111111 -
b0 &
b0 ,
b10000000000101011 %
b10000000000101011 +
#1800000
b11111111111111111111111111111110 =
b11111111111111111111111111111111 >
b11111111111111111111111111111110 /
b11111111111111111111111111111111 0
b1110 (
b11111111111111111111111111111110 '
b11111111111111111111111111111110 -
b11111111111111111111111111111111 &
b11111111111111111111111111111111 ,
#1900000
b1000 @
b10000000000 !
b10000000000 7
1)
b1 =
b1010 >
0.
b1010000000 3
b1 /
b0 0
b1010 1
b1010 4
b0 ;
b1010000000 2
b1010000000 :
b1111 (
b10000000000 $
b1 '
b1 -
b0 &
b0 ,
b10000001010000000 %
b10000001010000000 +
#2000000
b1010 @
b1111000000000000000000 !
b1111000000000000000000 7
b11110000000000000000000000000000 =
b1010000010 3
b11110000000000000000000000000000 /
b10 ;
b1010000010 2
b1010000010 :
b10000 (
b1111000000000000000000 $
b11110000000000000000000000000000 '
b11110000000000000000000000000000 -
b10000001010000010 %
b10000001010000010 +
#2100000
b1001 @
b10000000000000000 !
b10000000000000000 7
1.
0)
b1 =
b10000 >
b100 3
b1 /
b10000 0
b0 1
b0 4
b100 ;
b100 2
b100 :
b10001 (
b10000000000000000 $
b1 '
b1 -
b10000 &
b10000 ,
b10000000000000100 %
b10000000000000100 +
#2200000
b1011 @
b1111000000000000000000000000 !
b1111000000000000000000000000 7
0.
b11110000000000000000000000000000 =
b100 >
b110 3
b11110000000000000000000000000000 /
b100 0
b110 ;
b110 2
b110 :
b10010 (
b1111000000000000000000000000 $
b11110000000000000000000000000000 '
b11110000000000000000000000000000 -
b100 &
b100 ,
b10000000000000110 %
b10000000000000110 +
#2300000
b11111111000000000000000000000000 !
b11111111000000000000000000000000 7
b1101 @
b111 3
b111 ;
b111 2
b111 :
b10011 (
b11111111000000000000000000000000 $
b10000000000000111 %
b10000000000000111 +
#2400000
b11111100000000000000000000000000 !
b11111100000000000000000000000000 7
b1100 @
b10 >
1)
b10000011 3
b10 1
b10 4
b11 ;
b10000011 2
b10000011 :
b10100 (
b11111100000000000000000000000000 $
b10000000010000011 %
b10000000010000011 +
#2500000
b1 !
b1 7
b0 @
b0 "
b0 <
1*
b11 ?
b1 =
0)
b0 >
b1 3
b1 /
b0 0
b1000 9
b1 6
b0 5
b0 1
b0 4
b1 ;
b1 2
b1 :
b10101 (
b1 $
b0 '
b0 -
b1 &
b1 ,
b100000001000000000000000000001 %
b100000001000000000000000000001 +
#2600000
b1 "
b1 <
b10000000000000000000000000000000 !
b10000000000000000000000000000000 7
b1111111111111111111111111111111 >
b1111111111111111111111111111111 0
b0 /
b0 6
b1 5
b10110 (
b1 #
b10000000000000000000000000000000 $
b1111111111111111111111111111111 &
b1111111111111111111111111111111 ,
b100000000000010000000000000001 %
b100000000000010000000000000001 +
#2700000
b100 @
b1 !
b1 7
b0 "
b0 <
b11111111111111111111111111111111 >
b11111111111111111111111111111111 0
b1100 9
b10111 (
b0 #
b1 $
b11111111111111111111111111111111 &
b11111111111111111111111111111111 ,
b110000000000010000000000000001 %
b110000000000010000000000000001 +
#2800000
b1000000000000001 !
b1000000000000001 7
b1 @
b1000000000000001 =
b0 >
b1 /
b11111111111111111000000000000001 3
b0 0
b1001 9
b1 6
b0 5
b10000 8
b1000000000000001 2
b1000000000000001 :
b11000 (
b1000000000000001 $
b1 &
b1 ,
b100100001000001000000000000001 %
b100100001000001000000000000001 +
#2900000
b110 @
b10001 !
b10001 7
b10000 >
b1 =
b10000 0
b1 3
b0 /
b1101 9
b0 6
b1 5
b0 8
b1 2
b1 :
b11001 (
b10001 $
b10000 &
b10000 ,
b110100000000010000000000000001 %
b110100000000010000000000000001 +
#3000000
b111 @
b10 !
b10 7
b11 =
b1 >
b11 3
b1 0
b1110 9
b11 ;
b11 2
b11 :
b11010 (
b10 $
b1 &
b1 ,
b111000000000010000000000000011 %
b111000000000010000000000000011 +
#3100000
b10 "
b10 <
b1110 @
b11111111111111111111111111111111 !
b11111111111111111111111111111111 7
b1 =
b0 >
b1 3
b0 0
b1010 9
b1 ;
b1 2
b1 :
b11011 (
b10 #
b11111111111111111111111111111111 $
b0 &
b0 ,
b101000000000010000000000000001 %
b101000000000010000000000000001 +
#3200000
b0 "
b0 <
b1 !
b1 7
b0 =
b1 >
b0 3
b1 0
b0 ;
b0 2
b0 :
b11100 (
b0 #
b1 $
b1 &
b1 ,
b101000000000010000000000000000 %
b101000000000010000000000000000 +
#3300000
b10 @
b100 "
b100 <
b0 !
b0 7
b1 ?
b1 =
0*
b1 3
b1 /
b100 9
b1 ;
b1 2
b1 :
b11101 (
b100 #
b0 $
b1 '
b1 -
b10000000000010000000000000001 %
b10000000000010000000000000001 +
#3400000
b0 "
b0 <
b11111111111111111111111111111111 !
b11111111111111111111111111111111 7
b0 >
b0 0
b11110 (
b0 #
b11111111111111111111111111111111 $
b0 &
b0 ,
#3500000
b0 "
b0 <
b1 !
b1 7
0*
b0 =
b1 >
b0 /
b1 0
b101 9
b11111 (
b1 $
b0 '
b0 -
b1 &
b1 ,
b10100000000010000000000000001 %
b10100000000010000000000000001 +
#3600000
b100 "
b100 <
b0 !
b0 7
b1 =
b1 /
b100000 (
b100 #
b0 $
b1 '
b1 -
#3700000
b1111 @
b11111111111111111111111111110001 !
b11111111111111111111111111110001 7
1*
b11 ?
b10 "
b10 <
b10000 =
b10000 3
b0 /
b1011 9
b10000 ;
b10000 2
b10000 :
b100001 (
b10 #
b11111111111111111111111111110001 $
b0 '
b0 -
b101100000000010000000000010000 %
b101100000000010000000000010000 +
#3800000
b0 "
b0 <
b0 !
b0 7
b10000 >
b10000 0
b100010 (
b0 #
b0 $
b10000 &
b10000 ,
#3900000
b0 @
b11111111111111111111000000011111 !
b11111111111111111111000000011111 7
b0 ?
b11111111111111111111000000001111 =
b11111111111111111111000000001111 3
b100011 9
b11110 8
b1111 ;
b1111000000001111 2
b1111000000001111 :
b100011 (
b11111111111111111111000000011111 $
b10001100000000011111000000001111 %
b10001100000000011111000000001111 +
#4000000
b111000000001111 =
b111000100001111 !
b111000100001111 7
b100000000 >
b111000000001111 3
b100000000 0
b101011 9
b1110 8
b111000000001111 2
b111000000001111 :
b100100 (
b111000100001111 $
b100000000 &
b100000000 ,
b10101100000000010111000000001111 %
b10101100000000010111000000001111 +
